torch_optimizer/__init__.py
torch_optimizer/a2grad.py
torch_optimizer/accsgd.py
torch_optimizer/adabelief.py
torch_optimizer/adabound.py
torch_optimizer/adafactor.py
torch_optimizer/adahessian.py
torch_optimizer/adamod.py
torch_optimizer/adamp.py
torch_optimizer/aggmo.py
torch_optimizer/apollo.py
torch_optimizer/diffgrad.py
torch_optimizer/lamb.py
torch_optimizer/lars.py
torch_optimizer/lookahead.py
torch_optimizer/madgrad.py
torch_optimizer/novograd.py
torch_optimizer/pid.py
torch_optimizer/py.typed
torch_optimizer/qhadam.py
torch_optimizer/qhm.py
torch_optimizer/radam.py
torch_optimizer/sgdp.py
torch_optimizer/sgdw.py
torch_optimizer/shampoo.py
torch_optimizer/swats.py
torch_optimizer/types.py
torch_optimizer/yogi.py
torch_optimizer-0.3.0.dist-info/LICENSE
torch_optimizer-0.3.0.dist-info/METADATA
torch_optimizer-0.3.0.dist-info/WHEEL
torch_optimizer-0.3.0.dist-info/top_level.txt
torch_optimizer-0.3.0.dist-info/zip-safe
torch_optimizer-0.3.0.dist-info/RECORD
