Metadata-Version: 2.1
Name: torch-optimizer
Version: 0.3.0
Summary: pytorch-optimizer
Home-page: https://github.com/jettify/pytorch-optimizer
Author: Nikolay Novik
Author-email: nickolainovik@gmail.com
License: Apache 2
Download-URL: https://pypi.org/project/torch-optimizer/
Project-URL: Website, https://github.com/jettify/pytorch-optimizer
Project-URL: Documentation, https://pytorch-optimizer.readthedocs.io
Project-URL: Issues, https://github.com/jettify/pytorch-optimizer/issues
Keywords: torch-optimizer,pytorch,accsgd,adabound,adamod,diffgrad,lamb,lookahead,madgrad,novograd,pid,qhadam,qhm,radam,sgdw,yogi,ranger
Platform: POSIX
Classifier: License :: OSI Approved :: Apache Software License
Classifier: Intended Audience :: Developers
Classifier: Intended Audience :: Science/Research
Classifier: Programming Language :: Python :: 3
Classifier: Programming Language :: Python :: 3.6
Classifier: Programming Language :: Python :: 3.7
Classifier: Programming Language :: Python :: 3.8
Classifier: Operating System :: OS Independent
Classifier: Development Status :: 3 - Alpha
Classifier: Topic :: Scientific/Engineering :: Artificial Intelligence
Requires-Python: >=3.6.0
